sp_svg_diagram/__init__.py
sp_svg_diagram/_core.cpython-38-darwin.so
sp_svg_diagram-0.1.dist-info/METADATA
sp_svg_diagram-0.1.dist-info/WHEEL
sp_svg_diagram-0.1.dist-info/licenses/LICENSE
sp_svg_diagram-0.1.dist-info/RECORD
