Metadata-Version: 2.2
Name: sp-svg-diagram
Version: 0.1
Summary: A library for rendering diagrams to SVG.
License: MIT
Classifier: Programming Language :: Python :: 3
Classifier: Programming Language :: C++
Classifier: Operating System :: OS Independent
Requires-Python: >=3.8
Provides-Extra: test
Requires-Dist: pytest; extra == "test"
Requires-Dist: black; extra == "test"
Requires-Dist: isort; extra == "test"
Requires-Dist: flake8; extra == "test"
